pluscal/__init__.py
pluscal/api.py
pluscal/ast/__init__.py
pluscal/ast/algorithm.py
pluscal/ast/base.py
pluscal/ast/definition.py
pluscal/ast/macro.py
pluscal/ast/procedure.py
pluscal/ast/process.py
pluscal/ast/variable.py
pluscal/ast/statements/__init__.py
pluscal/ast/statements/assert_.py
pluscal/ast/statements/assign.py
pluscal/ast/statements/await_.py
pluscal/ast/statements/base.py
pluscal/ast/statements/call.py
pluscal/ast/statements/either.py
pluscal/ast/statements/goto.py
pluscal/ast/statements/if_.py
pluscal/ast/statements/print_.py
pluscal/ast/statements/return_.py
pluscal/ast/statements/skip.py
pluscal/ast/statements/while_.py
pluscal/ast/statements/with_.py
pluscal/builders/__init__.py
pluscal/builders/algorithm.py
pluscal/builders/assert_.py
pluscal/builders/assign.py
pluscal/builders/await_.py
pluscal/builders/base.py
pluscal/builders/body.py
pluscal/builders/call.py
pluscal/builders/definition.py
pluscal/builders/either.py
pluscal/builders/goto.py
pluscal/builders/if_.py
pluscal/builders/macro.py
pluscal/builders/print_.py
pluscal/builders/procedure.py
pluscal/builders/process.py
pluscal/builders/source.py
pluscal/builders/variable.py
pluscal/builders/while_.py
pluscal/builders/with_.py
pluscal-0.4.2.dist-info/LICENSE
pluscal-0.4.2.dist-info/METADATA
pluscal-0.4.2.dist-info/WHEEL
pluscal-0.4.2.dist-info/top_level.txt
pluscal-0.4.2.dist-info/RECORD
