Metadata-Version: 2.1
Name: pluscal
Version: 0.4.2
Summary: PlusCal AST and builder in Python
Home-page: https://github.com/jessemyers/pluscal
Author: Jesse Myers
License: Apache 2.0
Keywords: PlusCal TLA+
Platform: UNKNOWN
Classifier: Programming Language :: Python :: 3.7
Requires-Python: >=3.7
Provides-Extra: dist
Requires-Dist: bumpversion (>=0.5.3) ; extra == 'dist'
Requires-Dist: pip (>=19.0.3) ; extra == 'dist'
Requires-Dist: setuptools (>=40.8.0) ; extra == 'dist'
Requires-Dist: twine (>=1.13.0) ; extra == 'dist'
Requires-Dist: wheel (>=0.33.1) ; extra == 'dist'
Provides-Extra: lint
Requires-Dist: flake8 (>=3.7.7) ; extra == 'lint'
Requires-Dist: flake8-isort (>=2.7.0) ; extra == 'lint'
Requires-Dist: flake8-print (>=3.1.0) ; extra == 'lint'
Provides-Extra: test
Requires-Dist: coverage (>=4.5.3) ; extra == 'test'
Requires-Dist: nose (>=1.3.7) ; extra == 'test'
Requires-Dist: PyHamcrest (>=1.9.0) ; extra == 'test'
Provides-Extra: typehinting
Requires-Dist: mypy (>=0.670.0) ; extra == 'typehinting'
